fpstracker/__init__.py
fpstracker/main.py
fpstracker-1.0.0.dist-info/LICENSE.txt
fpstracker-1.0.0.dist-info/METADATA
fpstracker-1.0.0.dist-info/WHEEL
fpstracker-1.0.0.dist-info/top_level.txt
fpstracker-1.0.0.dist-info/RECORD
