Metadata-Version: 2.1
Name: fpstracker
Version: 1.0.0
Summary: A Python package to detect and calculate the webcam frame rate per second in any system.
Author-email: Naveen kumar S <snaveenkumar343@gmail.com>
Project-URL: Homepage, https://github.com/0EnIgma1/FPS_tracker
Project-URL: Bug Tracker, https://github.com/0EnIgma1/FPS_tracker/issues
Classifier: Programming Language :: Python :: 3
Classifier: License :: OSI Approved :: MIT License
Classifier: Operating System :: OS Independent
Requires-Python: >=3.8
License-File: LICENSE.txt
